[
	{
		"id":"XC524257",
		"pitch":{
			"pitch_median":"452.256 Hz",
			"pitch_mean":"426.015 Hz",
			"pitch_standart_deviation":"70.879 Hz",
			"pitch_minimum":"278.712 Hz",
			"pitch_maximum":"496.686 Hz"
		},
		"pulses":{
			"pulses_number_of_pulses":142,
			"pulses_number_of_periods":128,
			"pulses_mean_period":"2.396131E-3 seconds",
			"pulses_standart_deviation_of_period":"0.521693E-3 seconds"
		},
		"voicing":{
			"voicing_fraction_of_locally_unvoiced_frames":"76.163%",
			"voicing_number_of_voice_breaks":7,
			"voicing_degree_of_voice_breaks":"68.710%"
		},
		"jitter":{
			"jitter_local":"10.622%",
			"jitter_local_absolute":"254.516E-6 seconds",
			"jitter_rap":"5.830%",
			"jitter_ppq5":"7.519%",
			"jitter_ddp":"17.491%"
		},
		"shimmer":{
			"shimmer_local":"13.216%",
			"shimmer_local_dB":"1.160 dB",
			"shimmer_apq3":"7.103%",
			"shimmer_apq5":"7.626%",
			"shimmer_dda":"21.308%"
		}
	},
	{
		"id":"XC524258",
		"pitch":{
			"pitch_median":"450.638 Hz",
			"pitch_mean":"419.343 Hz",
			"pitch_standart_deviation":"94.788 Hz",
			"pitch_minimum":"250.316 Hz",
			"pitch_maximum":"500.340 Hz"
		},
		"pulses":{
			"pulses_number_of_pulses":61,
			"pulses_number_of_periods":57,
			"pulses_mean_period":"2.351524E-3 seconds",
			"pulses_standart_deviation_of_period":"0.609446E-3 seconds"
		},
		"voicing":{
			"voicing_fraction_of_locally_unvoiced_frames":"61.728%",
			"voicing_number_of_voice_breaks":2,
			"voicing_degree_of_voice_breaks":"28.369%"
		},
		"jitter":{
			"jitter_local":"8.291%",
			"jitter_local_absolute":"194.960E-6 seconds",
			"jitter_rap":"4.478%",
			"jitter_ppq5":"4.760%",
			"jitter_ddp":"13.433%"
		},
		"shimmer":{
			"shimmer_local":"14.744%",
			"shimmer_local_dB":"1.257 dB",
			"shimmer_apq3":"7.723%",
			"shimmer_apq5":"10.152%",
			"shimmer_dda":"23.168%"
		}
	},
	{
		"id":"XC524263",
		"pitch":{
			"pitch_median":"426.684 Hz",
			"pitch_mean":"414.719 Hz",
			"pitch_standart_deviation":"43.969 Hz",
			"pitch_minimum":"303.498 Hz",
			"pitch_maximum":"497.932 Hz"
		},
		"pulses":{
			"pulses_number_of_pulses":412,
			"pulses_number_of_periods":365,
			"pulses_mean_period":"2.434513E-3 seconds",
			"pulses_standart_deviation_of_period":"0.426508E-3 seconds"
		},
		"voicing":{
			"voicing_fraction_of_locally_unvoiced_frames":"55.602%",
			"voicing_number_of_voice_breaks":4,
			"voicing_degree_of_voice_breaks":"53.772%"
		},
		"jitter":{
			"jitter_local":"8.718%",
			"jitter_local_absolute":"212.252E-6 seconds",
			"jitter_rap":"5.259%",
			"jitter_ppq5":"6.493%",
			"jitter_ddp":"15.778%"
		},
		"shimmer":{
			"shimmer_local":"17.624%",
			"shimmer_local_dB":"1.544 dB",
			"shimmer_apq3":"8.107%",
			"shimmer_apq5":"10.041%",
			"shimmer_dda":"24.322%"
		}
	},
	{
		"id":"XC524658",
		"pitch":{
			"pitch_median":"455.685 Hz",
			"pitch_mean":"446.872 Hz",
			"pitch_standart_deviation":"37.864 Hz",
			"pitch_minimum":"314.300 Hz",
			"pitch_maximum":"520.541 Hz"
		},
		"pulses":{
			"pulses_number_of_pulses":542,
			"pulses_number_of_periods":496,
			"pulses_mean_period":"2.173983E-3 seconds",
			"pulses_standart_deviation_of_period":"0.376037E-3 seconds"
		},
		"voicing":{
			"voicing_fraction_of_locally_unvoiced_frames":"53.030%",
			"voicing_number_of_voice_breaks":4,
			"voicing_degree_of_voice_breaks":"48.902%"
		},
		"jitter":{
			"jitter_local":"8.622%",
			"jitter_local_absolute":"187.436E-6 seconds",
			"jitter_rap":"4.791%",
			"jitter_ppq5":"6.009%",
			"jitter_ddp":"14.373%"
		},
		"shimmer":{		
			"shimmer_local":"17.986%",
			"shimmer_local_dB":"1.628 dB",
			"shimmer_apq3":"8.762%",
			"shimmer_apq5":"11.810%",
			"shimmer_dda":"26.285%"
			}
	},
	{
		"id":"XC524659",
		"pitch":{
			"pitch_median":"454.007 Hz",
			"pitch_mean":"453.960 Hz",
			"pitch_standart_deviation":"1.880 Hz",
			"pitch_minimum":"452.058 Hz",
			"pitch_maximum":"455.816 Hz"
		},
		"pulses":{
			"pulses_number_of_pulses":14,
			"pulses_number_of_periods":11,
			"pulses_mean_period":"2.093131E-3 seconds",
			"pulses_standart_deviation_of_period":"0.375701E-3 seconds"
		},
		"voicing":{
			"voicing_fraction_of_locally_unvoiced_frames":"91.228%",
			"voicing_number_of_voice_breaks":0,
			"voicing_degree_of_voice_breaks":0
		},
		"jitter":{
			"jitter_local":"6.868%",
			"jitter_local_absolute":"143.755E-6 seconds",
			"jitter_rap":"2.928%",
			"jitter_ppq5":"null",
			"jitter_ddp":"8.784%"
		},
		"shimmer":{
			"shimmer_local":"null",
			"shimmer_local_dB":"null",
			"shimmer_apq3":"null",
			"shimmer_apq5":"null",
			"shimmer_dda":"null"
		}
	}
]